<annotation>
    <folder>output</folder>
    <filename>0-color0-rotate_180-03.jpg</filename>
    <path>D:\DishRcognitionResource\bounding-box-augmentation-master\bounding-box-augmentation-master\output\0-color0-rotate_180-03.jpg</path>
    <source>
        <database>Unknown</database>
    </source>
    <size>
        <width>800</width>
        <height>600</height>
        <depth>3</depth>
    </size>
    <segmented>0</segmented>
    <object>
        <name>bowl_big</name>
        <pose>Unspecified</pose>
        <truncated>0</truncated>
        <difficult>0</difficult>
        <bndbox>
            <xmin>172</xmin>
            <ymin>107</ymin>
            <xmax>558</xmax>
            <ymax>477</ymax>
        </bndbox>
    </object>
</annotation>
